pyscws/__init__.py
pyscws/scws.cp311-win_amd64.pyd
pyscws/scws.pyi
pyscws-0.0.1.1.dist-info/METADATA
pyscws-0.0.1.1.dist-info/WHEEL
pyscws-0.0.1.1.dist-info/top_level.txt
pyscws-0.0.1.1.dist-info/RECORD
